sage/__init__.py
sage/checkpoint.py
sage/cli.py
sage/client.py
sage/config.py
sage/continuity.py
sage/default_skills.py
sage/embeddings.py
sage/errors.py
sage/headless.py
sage/history.py
sage/init.py
sage/knowledge.py
sage/logging.py
sage/mcp_server.py
sage/memory.py
sage/recovery.py
sage/salience.py
sage/session.py
sage/skill.py
sage/tasks.py
sage/templates.py
sage/transcript.py
sage/types.py
sage/utils.py
sage/watcher.py
sage/codebase/__init__.py
sage/codebase/chunker.py
sage/codebase/compiler.py
sage/codebase/core_files.py
sage/codebase/indexer.py
sage/codebase/models.py
sage/codebase/search.py
sage/plugins/__init__.py
sage/plugins/base.py
sage/plugins/events.py
sage/plugins/executor.py
sage/plugins/registry.py
sage/plugins/builtin/__init__.py
sage/plugins/builtin/checkpoint_queue.py
sage/plugins/builtin/recovery.py
sage/plugins/builtin/session.py
sage/triggers/__init__.py
sage/triggers/combiner.py
sage/triggers/linguistic.py
sage/triggers/structural.py
sage/triggers/types.py
tests/__init__.py
tests/conftest.py
tests/test_checkpoint.py
tests/test_cli.py
tests/test_cli_continuity.py
tests/test_client.py
tests/test_continuity.py
tests/test_default_skills.py
tests/test_embeddings.py
tests/test_errors.py
tests/test_headless.py
tests/test_history.py
tests/test_integration.py
tests/test_knowledge.py
tests/test_logging.py
tests/test_mcp_async.py
tests/test_mcp_continuity.py
tests/test_mcp_server.py
tests/test_proactive_recall.py
tests/test_project_local.py
tests/test_recovery.py
tests/test_sage_config.py
tests/test_salience.py
tests/test_skill.py
tests/test_skills_cli.py
tests/test_tasks.py
tests/test_tasks_security.py
tests/test_templates.py
tests/test_transcript.py
tests/test_types.py
tests/test_version.py
tests/test_watcher.py
tests/codebase/__init__.py
tests/codebase/test_chunker.py
tests/codebase/test_compiler.py
tests/codebase/test_core_files.py
tests/codebase/test_indexer.py
tests/codebase/test_models.py
tests/codebase/test_search.py
tests/plugins/__init__.py
claude_sage-3.0.0.dist-info/METADATA
claude_sage-3.0.0.dist-info/WHEEL
claude_sage-3.0.0.dist-info/entry_points.txt
claude_sage-3.0.0.dist-info/top_level.txt
claude_sage-3.0.0.dist-info/RECORD
