Metadata-Version: 2.4
Name: claude-sage
Version: 3.0.0
Summary: Semantic checkpointing for Claude Code
License-Expression: MIT
Keywords: claude,claude-code,checkpointing,memory,mcp,ai
Classifier: Development Status :: 5 - Production/Stable
Classifier: Programming Language :: Python :: 3
Requires-Python: >=3.11
Requires-Dist: anthropic>=0.40.0
Requires-Dist: click>=8.0.0
Requires-Dist: rich>=13.0.0
Requires-Dist: pyyaml>=6.0.0
Requires-Dist: prompt-toolkit>=3.0.0
Requires-Dist: numpy>=1.24.0
Requires-Dist: sentence-transformers>=2.2.0
Requires-Dist: jinja2>=3.0.0
Provides-Extra: dev
Requires-Dist: pytest>=7.0.0; extra == "dev"
Requires-Dist: pytest-asyncio>=0.21.0; extra == "dev"
Requires-Dist: black>=23.0.0; extra == "dev"
Requires-Dist: ruff>=0.1.0; extra == "dev"
Provides-Extra: mcp
Requires-Dist: mcp>=1.2.0; extra == "mcp"
Provides-Extra: code
Requires-Dist: lancedb>=0.4.0; extra == "code"
Requires-Dist: tree-sitter-languages>=1.10.0; extra == "code"
